{
    "type": "metadata",
    "values": {
        "description": "Automatic indicators are indicators that automatically update from the underlying security data.",
        "keywords": "automatic updates registered for you, create automatic indicators, indicator helper methods, get the name of an indicator, create an indicator with the other fields, warm-up automatic indicators, Warm-up Helper Method",
        "og:description": "Automatic indicators are indicators that automatically update from the underlying security data.",
        "og:title": "Automatic Indicators - Documentation QuantConnect.com",
        "og:type": "website",
        "og:site_name": "Automatic Indicators - QuantConnect.com",
        "og:image": "https://cdn.quantconnect.com/docs/i/writing-algorithms/indicators/automatic-indicators.png"
    }
}
