{
    "type": "metadata",
    "values": {
        "description": "The Klinger Volume Oscillator (KVO) is a technical indicator that analyzes the relationship between price movement and trading ...",
        "keywords": "klinger volume oscillator",
        "og:type": "website",
        "og:description": "The Klinger Volume Oscillator (KVO) is a technical indicator that analyzes the relationship between price movement and trading ...",
        "og:title": "Klinger Volume Oscillator - Using Indicators on QuantConnect.com",
        "og:site_name": "Klinger Volume Oscillator - Using Indicators on QuantConnect.com",
        "og:image": "https://cdn.quantconnect.com/docs/i/writing-algorithms/indicators/supported-indicators/klinger-volume-oscillator.png"
    }
}