{
    "type": "metadata",
    "values": {
        "description": "This indicator computes the TRIX (1-period ROC of a Triple EMA) The TRIX is calculated as explained here: http://stockcharts.com/school/doku.php?id=chart_school:technical_indicators:trix",
        "keywords": "trix",
        "og:type": "website",
        "og:description": "This indicator computes the TRIX (1-period ROC of a Triple EMA) The TRIX is calculated as explained here: http://stockcharts.com/school/doku.php?id=chart_school:technical_indicators:trix",
        "og:title": "Trix - Using Indicators on QuantConnect.com",
        "og:site_name": "Trix - Using Indicators on QuantConnect.com",
        "og:image": "https://cdn.quantconnect.com/docs/i/writing-algorithms/indicators/supported-indicators/trix.png"
    }
}