{
    "type": "metadata",
    "values": {
        "description": "",
        "keywords": "equity options, immplied volatility, IV, option greeks, delta, gamma, vega, theta, rho",
        "og:description": "",
        "og:title": "The Greeks and Implied Volatility - Documentation QuantConnect.com",
        "og:type": "website",
        "og:site_name": "The Greeks and Implied Volatility - QuantConnect.com",
        "og:image": "https://cdn.quantconnect.com/docs/i/writing-algorithms/securities/asset-classes/equity-options/greeks-and-implied-volatility.png"
    }
}