
{
    "type": "metadata",
    "values": {
        "description": "Trading hours, holidays, and time zone of the Aluminium European Premium Duty-Paid (Metal Bulletin) Futures (EDP) contract in the COMEX Future market.",
        "keywords": "regular trading hours, pre-market hours, post-market hours, extended market hours, holidays, time zone",
        "og:description": "Trading hours, holidays, and time zone of the Aluminium European Premium Duty-Paid (Metal Bulletin) Futures (EDP) contract in the COMEX Future market.",
        "og:title": "EDP - Documentation QuantConnect.com",
        "og:type": "website",
        "og:site_name": "EDP - QuantConnect.com",
        "og:image": "https://cdn.quantconnect.com/web/i/docs/documentation_meta_image_rev0.png"

    }
}
