{
    "type": "metadata",
    "values": {
        "description": "Start Your QuantConnect Journey. Learn to use Local Platform and explore its features.",
        "keywords": "algorithmic model creation platform, local platform, projects, backtesting, local and cloud compute",
        "og:description": "Start Your QuantConnect Journey. Learn to use Local Platform and explore its features.",
        "og:title": "Local Platform - Documentation QuantConnect.com",
        "og:type": "website",
        "og:site_name": "Local Platform - QuantConnect.com",
        "og:image": "https://cdn.quantconnect.com/web/i/docs/documentation_meta_image_rev0.png"
    }
}
